weaviate_connection_pool/__init__.py
weaviate_connection_pool/pool.py
weaviate_connection_pool-0.1.0.dist-info/LICENSE.txt
weaviate_connection_pool-0.1.0.dist-info/METADATA
weaviate_connection_pool-0.1.0.dist-info/WHEEL
weaviate_connection_pool-0.1.0.dist-info/top_level.txt
weaviate_connection_pool-0.1.0.dist-info/RECORD
