Metadata-Version: 2.1
Name: weaviate-connection-pool
Version: 0.1.0
Summary: An efficient connection pool for Weaviate clients.
Home-page: https://github.com/Sushil2308/weaviate_connection_pool
Author: Sushil2308
Author-email: SushilPrasad60649@gmail.com
License: LICENSE.txt
Platform: UNKNOWN
Requires-Dist: weaviate-client >=2.5.0
